{
  "Verdun": {
    "\u00C5r": 1916,
    "Lat": 49.159,
    "Lon": 5.384,
    "Faktisk": "Frankrike forsvarte Verdun.",
    "Valg": {
      "Forsvar": {"Beskrivelse": "Frankrike holder linjen."},
      "Tilbaketrekning": {"Beskrivelse": "Frankrike trekker seg tilbake, Tyskland f\u00E5r overtak."}
    }
  },
  "Somme": {
    "\u00C5r": 1916,
    "Lat": 50.020,
    "Lon": 2.650,
    "Faktisk": "Store tap for britene.",
    "Valg": {
      "Frontalangrep": {"Beskrivelse": "Store tap, liten framgang."},
      "Utsette angrep": {"Beskrivelse": "Tyskland f\u00E5r tid til \u00E5 styrke linjene."}
    }
  },
  "Gallipoli": {
    "\u00C5r": 1915,
    "Lat": 40.000,
    "Lon": 26.000,
    "Faktisk": "Allierte styrker mislyktes i \u00E5 ta Dardanellene.",
    "Valg": {
      "Fortsett angrep": {"Beskrivelse": "Store tap, men press p\u00E5 Tyrkia øker."},
      "Trekk tilbake": {"Beskrivelse": "Bevarer styrker, men strategisk tap."}
    }
  },
  "Tannenberg": {
    "\u00C5r": 1914,
    "Lat": 53.866,
    "Lon": 20.533,
    "Faktisk": "Tyskland beseiret Russland.",
    "Valg": {
      "Aggressivt press": {"Beskrivelse": "Rask seier, Russland svekkes mer."},
      "Forsiktig manøver": {"Beskrivelse": "Lenger kamp, mindre tap men mindre framgang."}
    }
  },
  "Jutland": {
    "\u00C5r": 1916,
    "Lat": 56.950,
    "Lon": 7.667,
    "Faktisk": "Store tap p\u00E5 begge sider, ingen klar seier.",
    "Valg": {
      "Angrip umiddelbart": {"Beskrivelse": "Stor risiko, potensielt avgjørende seier."},
      "Hold posisjon": {"Beskrivelse": "Sikker, men uendret situasjon."}
    }
  },
  "Ypres": {
    "\u00C5r": 1915,
    "Lat": 50.850,
    "Lon": 2.883,
    "Faktisk": "Kjemisk krigføring introdusert, store tap.",
    "Valg": {
      "Fortsett offensiv": {"Beskrivelse": "Kan ta terreng, men høye tap."},
      "Stopp offensiv": {"Beskrivelse": "Reduserer tap, taper terreng."}
    }
  },
  "Caporetto": {
    "\u00C5r": 1917,
    "Lat": 46.016,
    "Lon": 12.566,
    "Faktisk": "Italienske styrker ble sl\u00E5tt tilbake kraftig.",
    "Valg": {
      "Fremrykk": {"Beskrivelse": "Stor risiko, kan vinne tilbake terreng."},
      "Trekk tilbake": {"Beskrivelse": "Bevarer styrker, men mister terreng."}
    }
  }
}
